dictionary/__init__.py
dictionary/dictionary.py
very_simple_dictionary_berk_kerem_bercin-2.0.2.dist-info/METADATA
very_simple_dictionary_berk_kerem_bercin-2.0.2.dist-info/WHEEL
very_simple_dictionary_berk_kerem_bercin-2.0.2.dist-info/top_level.txt
very_simple_dictionary_berk_kerem_bercin-2.0.2.dist-info/RECORD
