Metadata-Version: 2.1
Name: very-simple-dictionary-berk-kerem-bercin
Version: 2.0.2
Summary: UNKNOWN
Author: Berk Kerem Berçin
License: UNKNOWN
Platform: UNKNOWN
Requires-Python: >=3.8
Requires-Dist: requests (>=2.23.0)
